dymo_sdk/__about__.py
dymo_sdk/__init__.py
dymo_sdk/core.py
dymo_sdk/dlls/AWSSDK.Core.dll
dymo_sdk/dlls/AWSSDK.S3.dll
dymo_sdk/dlls/DYMO.CloudflareAddin.dll
dymo_sdk/dlls/DYMO.Common.dll
dymo_sdk/dlls/DYMO.CrossPlatform.Common.PlatformSpecific.dll
dymo_sdk/dlls/DYMO.CrossPlatform.Common.dll
dymo_sdk/dlls/DYMO.CrossPlatform.Services.dll
dymo_sdk/dlls/DYMO.LabelAPI.PlatformSpecific.dll
dymo_sdk/dlls/DYMO.LabelAPI.Skia.dll
dymo_sdk/dlls/DYMO.LabelAPI.dll
dymo_sdk/dlls/DYMO.PrinterCommands.dll
dymo_sdk/dlls/DYMOPrinting.dll
dymo_sdk/dlls/DymoSDK.dll
dymo_sdk/dlls/Microsoft.Bcl.AsyncInterfaces.dll
dymo_sdk/dlls/Microsoft.Windows.SDK.NET.dll
dymo_sdk/dlls/Newtonsoft.Json.dll
dymo_sdk/dlls/PrintingSupportLibrary.dll
dymo_sdk/dlls/QRCoder.dll
dymo_sdk/dlls/SkiaSharp.Views.Desktop.Common.dll
dymo_sdk/dlls/SkiaSharp.dll
dymo_sdk/dlls/System.Data.OleDb.dll
dymo_sdk/dlls/System.Management.dll
dymo_sdk/dlls/System.Reactive.dll
dymo_sdk/dlls/WinRT.Runtime.dll
dymo_sdk/dlls/Zeroconf.dll
dymo_sdk/dlls/libSkiaSharp.dll
dymo_sdk/dlls/usps4cb.dll
dymo_sdk-1.5.1b4.dist-info/METADATA
dymo_sdk-1.5.1b4.dist-info/WHEEL
dymo_sdk-1.5.1b4.dist-info/RECORD
