Metadata-Version: 2.4
Name: dymo_sdk
Version: 1.5.1b4
Summary: A package that interacts with DYMO Printers.
Project-URL: Homepage, https://github.com/dymosoftware/DCD-SDK-Python-Sample
Project-URL: Documentation, https://dymosoftware.github.io/DCD-SDK-Python-Sample/
Author: Dymo Team
License-Expression: MIT
Classifier: Development Status :: 4 - Beta
Classifier: Programming Language :: C#
Classifier: Programming Language :: Python :: 3
Requires-Dist: packaging
Requires-Dist: pythonnet
